flash_mm/__init__.py
flash_mm/contrast_matrix.py
flash_mm/lmm.py
flash_mm/lmmfit.py
flash_mm/lmmtest.py
flash_mm/sslmm.py
flash_mm-0.1.0.dist-info/licenses/LICENSE
flash_mm-0.1.0.dist-info/METADATA
flash_mm-0.1.0.dist-info/WHEEL
flash_mm-0.1.0.dist-info/top_level.txt
flash_mm-0.1.0.dist-info/RECORD
