Metadata-Version: 2.4
Name: FLASH-MM
Version: 0.1.0
Summary: Fast, scalable, and memory-efficient algorithm for fitting linear mixed-effects models (LMMs)
Author-email: Changjiang Xu <changjiang.xu@utoronto.ca>, Delaram Pouyabahar <d.pouyabahar@mail.utoronto.ca>, Veronique Voisin <veronique.voisin@gmail.com>, Gary Bader <gary.bader@utoronto.ca>
Maintainer-email: Changjiang Xu <changjiang.xu@utoronto.ca>
License-Expression: MIT
Project-URL: Homepage, https://github.com/BaderLab/FLASHMM
Project-URL: Documentation, https://cran.r-project.org/web/packages/FLASHMM/vignettes/FLASHMM-vignette.html
Keywords: mixed-effects model,large-scale data,single-cell differential expression
Classifier: Development Status :: 4 - Beta
Classifier: Programming Language :: Python
Classifier: Programming Language :: Python :: 3.13
Requires-Python: >=3.8
License-File: LICENSE
Requires-Dist: numpy
Requires-Dist: pandas
Dynamic: license-file
